{
    "species": {
        "bluegill": "Bluegill",
        "brownTrout": "Brown Trout",
        "channelCatfish": "Channel Catfish",
        "commonCarp": "Common Carp",
        "largemouthBass": "Largemouth Bass",
        "northernSnakehead": "Northern Snakehead",
        "rainbowTrout": "Rainbow Trout",
        "redbreastSunfish": "Redbreast Sunfish",
        "smallmouthBass": "Smallmouth Bass"
    },
    "lures": {
        "jerkbait": "Jerkbait",
        "crankbait": "Crankbait",
        "rubberWorm": "Rubber Worm",
        "jig": "Jig",
        "spinnerbait": "Spinnerbait"
    },
    "cloudConditions": {
        "mostlySunny": "Mostly Sunny",
        "partlyCloudy": "Partly Cloudy",
        "mostlyCloudy": "Mostly Cloudy",
        "lightShowers": "Light Showers",
        "heavyRain": "Heavy Rain",
        "thunderstorms": "Thunderstorms",
        "snow": "Snow"
    },
    "waterClarities": {
        "clear": "Clear",
        "partlyStained": "Partly Stained",
        "stained": "Stained"
    },
    "waterTypes": {
        "freshwater": "freshwater",
        "saltwater": "saltwater"
    }
}